lires/__init__.py
lires/confReader.py
lires/exec.py
lires/initLogger.py
lires/parser.py
lires/version.py
lires/version.yaml
lires/assets/pdf-viewer/LICENSE
lires/assets/pdf-viewer/build/pdf.mjs
lires/assets/pdf-viewer/build/pdf.mjs.map
lires/assets/pdf-viewer/build/pdf.sandbox.mjs
lires/assets/pdf-viewer/build/pdf.sandbox.mjs.map
lires/assets/pdf-viewer/build/pdf.worker.mjs
lires/assets/pdf-viewer/build/pdf.worker.mjs.map
lires/assets/pdf-viewer/web/compressed.tracemonkey-pldi-09.pdf
lires/assets/pdf-viewer/web/debugger.css
lires/assets/pdf-viewer/web/debugger.mjs
lires/assets/pdf-viewer/web/viewer.css
lires/assets/pdf-viewer/web/viewer.html
lires/assets/pdf-viewer/web/viewer.mjs
lires/assets/pdf-viewer/web/viewer.mjs.map
lires/assets/pdf-viewer/web/cmaps/78-EUC-H.bcmap
lires/assets/pdf-viewer/web/cmaps/78-EUC-V.bcmap
lires/assets/pdf-viewer/web/cmaps/78-H.bcmap
lires/assets/pdf-viewer/web/cmaps/78-RKSJ-H.bcmap
lires/assets/pdf-viewer/web/cmaps/78-RKSJ-V.bcmap
lires/assets/pdf-viewer/web/cmaps/78-V.bcmap
lires/assets/pdf-viewer/web/cmaps/78ms-RKSJ-H.bcmap
lires/assets/pdf-viewer/web/cmaps/78ms-RKSJ-V.bcmap
lires/assets/pdf-viewer/web/cmaps/83pv-RKSJ-H.bcmap
lires/assets/pdf-viewer/web/cmaps/90ms-RKSJ-H.bcmap
lires/assets/pdf-viewer/web/cmaps/90ms-RKSJ-V.bcmap
lires/assets/pdf-viewer/web/cmaps/90msp-RKSJ-H.bcmap
lires/assets/pdf-viewer/web/cmaps/90msp-RKSJ-V.bcmap
lires/assets/pdf-viewer/web/cmaps/90pv-RKSJ-H.bcmap
lires/assets/pdf-viewer/web/cmaps/90pv-RKSJ-V.bcmap
lires/assets/pdf-viewer/web/cmaps/Add-H.bcmap
lires/assets/pdf-viewer/web/cmaps/Add-RKSJ-H.bcmap
lires/assets/pdf-viewer/web/cmaps/Add-RKSJ-V.bcmap
lires/assets/pdf-viewer/web/cmaps/Add-V.bcmap
lires/assets/pdf-viewer/web/cmaps/Adobe-CNS1-0.bcmap
lires/assets/pdf-viewer/web/cmaps/Adobe-CNS1-1.bcmap
lires/assets/pdf-viewer/web/cmaps/Adobe-CNS1-2.bcmap
lires/assets/pdf-viewer/web/cmaps/Adobe-CNS1-3.bcmap
lires/assets/pdf-viewer/web/cmaps/Adobe-CNS1-4.bcmap
Lires-1.3.3.dist-info/LICENSE
Lires-1.3.3.dist-info/METADATA
Lires-1.3.3.dist-info/WHEEL
Lires-1.3.3.dist-info/entry_points.txt
Lires-1.3.3.dist-info/top_level.txt
Lires-1.3.3.dist-info/RECORD
