Metadata-Version: 2.1
Name: Lires
Version: 1.3.3
Summary: A research bibliography manager
Author-email: "Li, Mengxun" <mengxunli@whu.edu.cn>
License: GNU GENERAL PUBLIC LICENSE
Project-URL: Homepage, https://github.com/MenxLi/ResBibManager
Project-URL: Bug Tracker, https://github.com/MenxLi/ResBibManager/issues
Classifier: Programming Language :: Python :: 3
Classifier: Operating System :: OS Independent
Classifier: Topic :: Scientific/Engineering :: Medical Science Apps.
Requires-Python: >=3.8
License-File: LICENSE
Requires-Dist: pyyaml
Requires-Dist: requests
Requires-Dist: deprecated
Provides-Extra: ai
Requires-Dist: safetensors (<=0.3.2) ; extra == 'ai'
Requires-Dist: torch ; extra == 'ai'
Requires-Dist: openai ; extra == 'ai'
Requires-Dist: transformers ; extra == 'ai'
Requires-Dist: fastapi[all] ; extra == 'ai'
Requires-Dist: sentencepiece ; extra == 'ai'
Requires-Dist: protobuf ; extra == 'ai'
Requires-Dist: accelerate ; extra == 'ai'
Requires-Dist: basaran ; extra == 'ai'
Provides-Extra: all
Requires-Dist: Lires[ai,core] ; extra == 'all'
Provides-Extra: core
Requires-Dist: typing-extensions ; extra == 'core'
Requires-Dist: tiny-vectordb ; extra == 'core'
Requires-Dist: pybtex ; extra == 'core'
Requires-Dist: pylatexenc ; extra == 'core'
Requires-Dist: tornado ; extra == 'core'
Requires-Dist: PyMuPDF ; extra == 'core'
Requires-Dist: nbib ; extra == 'core'
Requires-Dist: tqdm ; extra == 'core'
Requires-Dist: pillow ; extra == 'core'
Requires-Dist: numpy ; extra == 'core'
Requires-Dist: scikit-learn ; extra == 'core'
